streamlit_msal_imperial_component/__init__.py
streamlit_msal_imperial_component/frontend/dist/bootstrap.min.css
streamlit_msal_imperial_component/frontend/dist/index.html
streamlit_msal_imperial_component/frontend/dist/assets/browse-f1c3c92d.png
streamlit_msal_imperial_component/frontend/dist/assets/file-2ded6d26.png
streamlit_msal_imperial_component/frontend/dist/assets/imperial-46d46eff.png
streamlit_msal_imperial_component/frontend/dist/assets/index-c76dd259.css
streamlit_msal_imperial_component/frontend/dist/assets/index-cf7300df.js
streamlit_msal_imperial_component/frontend/dist/assets/model_history-98679c4f.png
streamlit_msal_imperial_component/frontend/dist/assets/optimisation_target-c203dbd5.png
streamlit_msal_imperial_component/frontend/dist/assets/order_icon-ce654517.png
streamlit_msal_imperial_component/frontend/dist/assets/plus_icon-4e34980b.png
streamlit_msal_imperial_component/frontend/dist/assets/question_mark-ab0c81ff.png
streamlit_msal_imperial_component/frontend/dist/assets/search-0657c804.png
streamlit_msal_imperial_component/frontend/dist/assets/vector-c47a212d.png
streamlit_msal_imperial_component/frontend/dist/static/custom_css/custom.css
streamlit_msal_imperial_component/frontend/dist/static/images/browse.png
streamlit_msal_imperial_component/frontend/dist/static/images/download_icon.png
streamlit_msal_imperial_component/frontend/dist/static/images/excel_icon.png
streamlit_msal_imperial_component/frontend/dist/static/images/image 1.png
streamlit_msal_imperial_component/frontend/dist/static/images/imperial.png
streamlit_msal_imperial_component/frontend/dist/static/images/logo.PNG
streamlit_msal_imperial_component/frontend/dist/static/images/optimisation_target.png
streamlit_msal_imperial_component/frontend/dist/static/images/order_icon.png
streamlit_msal_imperial_component/frontend/dist/static/images/output.png
streamlit_msal_imperial_component/frontend/dist/static/images/plus_icon.png
streamlit_msal_imperial_component-3.0.7.dist-info/LICENSE
streamlit_msal_imperial_component-3.0.7.dist-info/METADATA
streamlit_msal_imperial_component-3.0.7.dist-info/WHEEL
streamlit_msal_imperial_component-3.0.7.dist-info/top_level.txt
streamlit_msal_imperial_component-3.0.7.dist-info/RECORD
