Metadata-Version: 2.1
Name: streamlit-msal-imperial-component
Version: 3.0.7
Summary: added view output
Home-page: UNKNOWN
Author: 
Author-email: 
License: UNKNOWN
Platform: UNKNOWN
Requires-Python: >=3.6
Requires-Dist: streamlit (>=1.36)
